pupil/__init__.py
pupil/annotation.py
pupil/db/__init__.py
pupil/db/database.py
pupil/db/meta.py
pupil/db/vector.py
pupil/models/__init__.py
pupil/models/clustering.py
pupil/pupil.py
pupil/sampling/__init__.py
pupil/sampling/base.py
pupil/sampling/cluster_based.py
pupil/sampling/model_based.py
pupil/sampling/uncertainty.py
pupil/types.py
pupil-0.2.0.dist-info/LICENSE
pupil-0.2.0.dist-info/WHEEL
pupil-0.2.0.dist-info/METADATA
pupil-0.2.0.dist-info/RECORD
